crypto_py/CryptoPY.py
crypto_py/SMPY.py
crypto_py/__init__.py
crypto_py/__version__.py
crypto_py/AES/__init__.py
crypto_py/AES/_aes.py
crypto_py/SM4/__init__.py
crypto_py/SM4/_constant.py
crypto_py/SM4/_sm4.py
crypto_py/enc/__init__.py
crypto_py/enc/enc.py
crypto_py/mode/__init__.py
crypto_py/mode/mode.py
crypto_py/models/__init__.py
crypto_py/models/_data_models.py
crypto_py/models/_options.py
crypto_py/pad/__init__.py
crypto_py/pad/pad.py
crypto_js_to_py-0.2.2.dist-info/LICENSE
crypto_js_to_py-0.2.2.dist-info/METADATA
crypto_js_to_py-0.2.2.dist-info/WHEEL
crypto_js_to_py-0.2.2.dist-info/top_level.txt
crypto_js_to_py-0.2.2.dist-info/RECORD
