Metadata-Version: 2.1
Name: crypto-js-to-py
Version: 0.2.2
Summary: 基于pycryptodomex的二次封装,对CryptoJS的AES和CBC进行了简单的复刻
Home-page: UNKNOWN
Author: Primice
Author-email: 1121796946@qq.com
License: MIT
Platform: UNKNOWN
Classifier: Programming Language :: Python :: 3
Classifier: License :: OSI Approved :: MIT License
Classifier: Operating System :: OS Independent
License-File: LICENSE
Requires-Dist: pycryptodomex
Requires-Dist: pydantic
